fastapi_oidc_backend/__init__.py
fastapi_oidc_backend/exceptions.py
fastapi_oidc_backend/models.py
fastapi_oidc_backend/security.py
fastapi_oidc_backend-0.6.0.dist-info/LICENSE
fastapi_oidc_backend-0.6.0.dist-info/METADATA
fastapi_oidc_backend-0.6.0.dist-info/WHEEL
fastapi_oidc_backend-0.6.0.dist-info/RECORD
