Metadata-Version: 2.1
Name: fastapi-oidc-backend
Version: 0.6.0
Summary: Build resource servers with FastAPI
Home-page: https://github.com/BlackVoid/fastapi-oidc-backend
License: MIT
Keywords: fastapi,authentication,oidc,openidconnect
Author: Felix Gustavsson
Author-email: felix@0b1.se
Requires-Python: >=3.11.2,<4.0.0
Classifier: Development Status :: 4 - Beta
Classifier: Environment :: Web Environment
Classifier: Intended Audience :: Developers
Classifier: Intended Audience :: Information Technology
Classifier: License :: OSI Approved :: MIT License
Classifier: Programming Language :: Python :: 3
Classifier: Programming Language :: Python :: 3.12
Classifier: Programming Language :: Python :: 3 :: Only
Classifier: Programming Language :: Python :: 3.6
Classifier: Topic :: Internet
Classifier: Topic :: Internet :: WWW/HTTP
Classifier: Topic :: Internet :: WWW/HTTP :: HTTP Servers
Classifier: Topic :: Software Development :: Libraries
Classifier: Topic :: Software Development :: Libraries :: Application Frameworks
Classifier: Topic :: Software Development :: Libraries :: Python Modules
Requires-Dist: fastapi (>=0,<1)
Requires-Dist: httpx (>=0.27.0,<0.28.0)
Requires-Dist: pyjwt[crypto] (>=2.8.0,<3.0.0)
Project-URL: Repository, https://github.com/BlackVoid/fastapi-oidc-backend
